<?xml version="1.0" encoding="UTF-8"?>

<FLOW VERSION="3.0" CLEANUP="true">
  <COMMENT></COMMENT>

  <!-- nodes -->

<INVOKE TIMEOUT="" SERVICE="wm.tn.doc:getContentPartData" VALIDATE-IN="$none" VALIDATE-OUT="$none">
  <COMMENT></COMMENT>

  <!-- nodes -->

<MAP MODE="INPUT">
  <MAPTARGET>

<Values version="2.0">
  <record name="xml" javaclass="com.wm.util.Values">
    <value name="node_type">record</value>
    <value name="field_name">getContentPartDataInput</value>
    <value name="field_type">record</value>
    <value name="field_dim">0</value>
    <value name="nillable">true</value>
    <array name="rec_fields" type="record" depth="1">
      <record javaclass="com.wm.util.Values">
        <value name="node_type">unknown</value>
        <value name="field_name">bizdoc</value>
        <value name="field_type">object</value>
        <value name="field_dim">0</value>
        <value name="nillable">true</value>
      </record>
      <record javaclass="com.wm.util.Values">
        <value name="node_type">unknown</value>
        <value name="field_name">partName</value>
        <value name="field_type">string</value>
        <value name="field_dim">0</value>
        <value name="nillable">true</value>
      </record>
      <record javaclass="com.wm.util.Values">
        <value name="node_type">unknown</value>
        <value name="field_name">getAs</value>
        <value name="field_type">string</value>
        <value name="field_dim">0</value>
        <array name="field_options" type="value" depth="1">
          <value>bytes</value>
          <value>stream</value>
        </array>
        <value name="nillable">true</value>
      </record>
      <record javaclass="com.wm.util.Values">
        <value name="node_type">unknown</value>
        <value name="field_name">startIndex</value>
        <value name="field_type">string</value>
        <value name="field_dim">0</value>
        <value name="field_opt">true</value>
        <value name="nillable">true</value>
      </record>
      <record javaclass="com.wm.util.Values">
        <value name="node_type">unknown</value>
        <value name="field_name">byteCount</value>
        <value name="field_type">string</value>
        <value name="field_dim">0</value>
        <value name="field_opt">true</value>
        <value name="nillable">true</value>
      </record>
    </array>
  </record>
</Values>
</MAPTARGET>
  <MAPSOURCE>

<Values version="2.0">
  <record name="xml" javaclass="com.wm.util.Values">
    <value name="node_type">record</value>
    <value name="field_type">record</value>
    <value name="field_dim">0</value>
    <value name="nillable">true</value>
    <array name="rec_fields" type="record" depth="1">
    </array>
  </record>
</Values>
</MAPSOURCE>

  <!-- nodes -->

<MAPSET NAME="Setter" OVERWRITE="true" VARIABLES="false" FIELD="/getAs;1;0">
  <DATA ENCODING="XMLValues" I18N="true">

<Values version="2.0">
  <value name="xml">stream</value>
  <record name="type" javaclass="com.wm.util.Values">
    <value name="node_type">unknown</value>
    <value name="field_name">getAs</value>
    <value name="field_type">string</value>
    <value name="field_dim">0</value>
    <array name="field_options" type="value" depth="1">
      <value>bytes</value>
      <value>stream</value>
    </array>
    <value name="nillable">true</value>
  </record>
</Values>
</DATA>
</MAPSET>

<MAPSET NAME="Setter" OVERWRITE="true" VARIABLES="false" FIELD="/partName;1;0">
  <DATA ENCODING="XMLValues" I18N="true">

<Values version="2.0">
  <value name="xml">xmldata</value>
  <record name="type" javaclass="com.wm.util.Values">
    <value name="node_type">unknown</value>
    <value name="field_name">partName</value>
    <value name="field_type">string</value>
    <value name="field_dim">0</value>
    <value name="nillable">true</value>
  </record>
</Values>
</DATA>
</MAPSET>
</MAP>

<MAP MODE="OUTPUT">
  <MAPTARGET>

<Values version="2.0">
  <record name="xml" javaclass="com.wm.util.Values">
    <value name="node_type">record</value>
    <value name="field_type">record</value>
    <value name="field_dim">0</value>
    <value name="nillable">true</value>
    <array name="rec_fields" type="record" depth="1">
      <record javaclass="com.wm.util.Values">
        <value name="node_type">unknown</value>
        <value name="field_name">fileName</value>
        <value name="field_type">string</value>
        <value name="field_dim">0</value>
        <value name="nillable">true</value>
      </record>
      <record javaclass="com.wm.util.Values">
        <value name="node_type">record</value>
        <value name="node_comment"></value>
        <record name="node_hints" javaclass="com.wm.util.Values">
          <value name="field_largerEditor">false</value>
          <value name="field_password">false</value>
        </record>
        <value name="field_name">bizdoc</value>
        <value name="field_type">recref</value>
        <value name="field_dim">0</value>
        <value name="nillable">true</value>
        <value name="rec_closed">true</value>
        <value name="rec_ref">wm.tn.rec:BizDocType</value>
      </record>
      <record javaclass="com.wm.util.Values">
        <value name="node_type">unknown</value>
        <value name="field_name">partName</value>
        <value name="field_type">string</value>
        <value name="field_dim">0</value>
        <value name="nillable">true</value>
      </record>
      <record javaclass="com.wm.util.Values">
        <value name="node_type">unknown</value>
        <value name="field_name">getAs</value>
        <value name="field_type">string</value>
        <value name="field_dim">0</value>
        <value name="nillable">true</value>
      </record>
      <record javaclass="com.wm.util.Values">
        <value name="node_type">unknown</value>
        <value name="field_name">partContent</value>
        <value name="field_type">object</value>
        <value name="field_dim">0</value>
        <value name="nillable">true</value>
      </record>
    </array>
  </record>
</Values>
</MAPTARGET>
  <MAPSOURCE>

<Values version="2.0">
  <record name="xml" javaclass="com.wm.util.Values">
    <value name="node_type">record</value>
    <value name="field_name">getContentPartDataOutput</value>
    <value name="field_type">record</value>
    <value name="field_dim">0</value>
    <value name="nillable">true</value>
    <array name="rec_fields" type="record" depth="1">
    </array>
  </record>
</Values>
</MAPSOURCE>

  <!-- nodes -->

<MAPDELETE NAME="Dropper" FIELD="/fileName;1;0">
</MAPDELETE>

<MAPDELETE NAME="Dropper" FIELD="/partName;1;0">
</MAPDELETE>

<MAPDELETE NAME="Dropper" FIELD="/getAs;1;0">
</MAPDELETE>
</MAP>
</INVOKE>

<INVOKE TIMEOUT="" SERVICE="pub.xml:xmlStringToXMLNode" VALIDATE-IN="$none" VALIDATE-OUT="$none">
  <COMMENT></COMMENT>

  <!-- nodes -->

<MAP MODE="INPUT">
  <MAPTARGET>

<Values version="2.0">
  <record name="xml" javaclass="com.wm.util.Values">
    <value name="node_type">record</value>
    <value name="field_name">xmlStringToXMLNodeInput</value>
    <value name="field_type">record</value>
    <value name="field_dim">0</value>
    <value name="nillable">true</value>
    <array name="rec_fields" type="record" depth="1">
      <record javaclass="com.wm.util.Values">
        <value name="node_type">unknown</value>
        <value name="field_name">xmldata</value>
        <value name="field_type">string</value>
        <value name="field_dim">0</value>
        <value name="field_opt">true</value>
        <value name="nillable">true</value>
      </record>
      <record javaclass="com.wm.util.Values">
        <value name="node_type">unknown</value>
        <value name="field_name">$filedata</value>
        <value name="field_type">object</value>
        <value name="field_dim">0</value>
        <value name="field_opt">true</value>
        <value name="nillable">true</value>
      </record>
      <record javaclass="com.wm.util.Values">
        <value name="node_type">unknown</value>
        <value name="field_name">$filestream</value>
        <value name="field_type">object</value>
        <value name="field_dim">0</value>
        <value name="field_opt">true</value>
        <value name="nillable">true</value>
      </record>
      <record javaclass="com.wm.util.Values">
        <value name="node_type">unknown</value>
        <value name="field_name">encoding</value>
        <value name="field_type">string</value>
        <value name="field_dim">0</value>
        <value name="field_opt">true</value>
        <value name="nillable">true</value>
      </record>
      <record javaclass="com.wm.util.Values">
        <value name="node_type">unknown</value>
        <value name="field_name">expandDTD</value>
        <value name="field_type">string</value>
        <value name="field_dim">0</value>
        <value name="field_opt">true</value>
        <array name="field_options" type="value" depth="1">
          <value>false</value>
          <value>true</value>
        </array>
        <value name="nillable">true</value>
      </record>
      <record javaclass="com.wm.util.Values">
        <value name="node_type">unknown</value>
        <value name="field_name">isXML</value>
        <value name="field_type">string</value>
        <value name="field_dim">0</value>
        <value name="field_opt">true</value>
        <array name="field_options" type="value" depth="1">
          <value>false</value>
          <value>true</value>
          <value>autoDetect</value>
        </array>
        <value name="nillable">true</value>
      </record>
    </array>
  </record>
</Values>
</MAPTARGET>
  <MAPSOURCE>

<Values version="2.0">
  <record name="xml" javaclass="com.wm.util.Values">
    <value name="node_type">record</value>
    <value name="field_type">record</value>
    <value name="field_dim">0</value>
    <value name="nillable">true</value>
    <array name="rec_fields" type="record" depth="1">
      <record javaclass="com.wm.util.Values">
        <value name="node_type">record</value>
        <value name="node_comment"></value>
        <record name="node_hints" javaclass="com.wm.util.Values">
          <value name="field_largerEditor">false</value>
          <value name="field_password">false</value>
        </record>
        <value name="field_name">bizdoc</value>
        <value name="field_type">recref</value>
        <value name="field_dim">0</value>
        <value name="nillable">true</value>
        <value name="rec_closed">true</value>
        <value name="rec_ref">wm.tn.rec:BizDocType</value>
      </record>
      <record javaclass="com.wm.util.Values">
        <value name="node_type">unknown</value>
        <value name="field_name">partContent</value>
        <value name="field_type">object</value>
        <value name="field_dim">0</value>
        <value name="nillable">true</value>
      </record>
    </array>
  </record>
</Values>
</MAPSOURCE>

  <!-- nodes -->

<MAPCOPY NAME="Link" FROM="/partContent;3;0" TO="/$filestream;3;0">
</MAPCOPY>

<MAPSET NAME="Setter" OVERWRITE="true" VARIABLES="false" FIELD="/isXML;1;0">
  <DATA ENCODING="XMLValues" I18N="true">

<Values version="2.0">
  <value name="xml">true</value>
  <record name="type" javaclass="com.wm.util.Values">
    <value name="node_type">unknown</value>
    <value name="field_name">isXML</value>
    <value name="field_type">string</value>
    <value name="field_dim">0</value>
    <value name="field_opt">true</value>
    <array name="field_options" type="value" depth="1">
      <value>false</value>
      <value>true</value>
      <value>autoDetect</value>
    </array>
    <value name="nillable">true</value>
  </record>
</Values>
</DATA>
</MAPSET>
</MAP>

<MAP MODE="OUTPUT">
  <MAPTARGET>

<Values version="2.0">
  <record name="xml" javaclass="com.wm.util.Values">
    <value name="node_type">record</value>
    <value name="field_type">record</value>
    <value name="field_dim">0</value>
    <value name="nillable">true</value>
    <array name="rec_fields" type="record" depth="1">
      <record javaclass="com.wm.util.Values">
        <value name="node_type">record</value>
        <value name="node_comment"></value>
        <record name="node_hints" javaclass="com.wm.util.Values">
          <value name="field_largerEditor">false</value>
          <value name="field_password">false</value>
        </record>
        <value name="field_name">bizdoc</value>
        <value name="field_type">recref</value>
        <value name="field_dim">0</value>
        <value name="nillable">true</value>
        <value name="rec_closed">true</value>
        <value name="rec_ref">wm.tn.rec:BizDocType</value>
      </record>
      <record javaclass="com.wm.util.Values">
        <value name="node_type">unknown</value>
        <value name="field_name">partContent</value>
        <value name="field_type">object</value>
        <value name="field_dim">0</value>
        <value name="nillable">true</value>
      </record>
      <record javaclass="com.wm.util.Values">
        <value name="node_type">unknown</value>
        <value name="field_name">$filestream</value>
        <value name="field_type">object</value>
        <value name="field_dim">0</value>
        <value name="nillable">true</value>
      </record>
      <record javaclass="com.wm.util.Values">
        <value name="node_type">unknown</value>
        <value name="field_name">isXML</value>
        <value name="field_type">string</value>
        <value name="field_dim">0</value>
        <value name="nillable">true</value>
      </record>
      <record javaclass="com.wm.util.Values">
        <value name="node_type">unknown</value>
        <value name="field_name">node</value>
        <value name="field_type">object</value>
        <value name="field_dim">0</value>
        <value name="nillable">true</value>
      </record>
    </array>
  </record>
</Values>
</MAPTARGET>
  <MAPSOURCE>

<Values version="2.0">
  <record name="xml" javaclass="com.wm.util.Values">
    <value name="node_type">record</value>
    <value name="field_name">xmlStringToXMLNodeOutput</value>
    <value name="field_type">record</value>
    <value name="field_dim">0</value>
    <value name="nillable">true</value>
    <array name="rec_fields" type="record" depth="1">
    </array>
  </record>
</Values>
</MAPSOURCE>

  <!-- nodes -->

<MAPDELETE NAME="Dropper" FIELD="/partContent;3;0">
</MAPDELETE>

<MAPDELETE NAME="Dropper" FIELD="/$filestream;3;0">
</MAPDELETE>

<MAPDELETE NAME="Dropper" FIELD="/isXML;1;0">
</MAPDELETE>
</MAP>
</INVOKE>

<INVOKE TIMEOUT="" SERVICE="pub.xml:xmlNodeToDocument" VALIDATE-IN="$none" VALIDATE-OUT="$none">
  <COMMENT></COMMENT>

  <!-- nodes -->

<MAP MODE="INPUT">
  <MAPTARGET>

<Values version="2.0">
  <record name="xml" javaclass="com.wm.util.Values">
    <value name="node_type">record</value>
    <value name="field_name">xmlNodeToDocumentInput</value>
    <value name="field_type">record</value>
    <value name="field_dim">0</value>
    <value name="nillable">true</value>
    <array name="rec_fields" type="record" depth="1">
      <record javaclass="com.wm.util.Values">
        <value name="node_type">unknown</value>
        <value name="field_name">node</value>
        <value name="field_type">object</value>
        <value name="field_dim">0</value>
        <value name="nillable">true</value>
      </record>
      <record javaclass="com.wm.util.Values">
        <value name="node_type">unknown</value>
        <value name="field_name">attrPrefix</value>
        <value name="field_type">string</value>
        <value name="field_dim">0</value>
        <value name="field_opt">true</value>
        <value name="nillable">true</value>
      </record>
      <record javaclass="com.wm.util.Values">
        <value name="node_type">unknown</value>
        <value name="field_name">arrays</value>
        <value name="field_type">string</value>
        <value name="field_dim">1</value>
        <value name="field_opt">true</value>
        <value name="nillable">true</value>
      </record>
      <record javaclass="com.wm.util.Values">
        <value name="node_type">unknown</value>
        <value name="field_name">makeArrays</value>
        <value name="field_type">string</value>
        <value name="field_dim">0</value>
        <value name="field_opt">true</value>
        <array name="field_options" type="value" depth="1">
          <value>true</value>
          <value>false</value>
        </array>
        <value name="nillable">true</value>
      </record>
      <record javaclass="com.wm.util.Values">
        <value name="node_type">record</value>
        <value name="field_name">collect</value>
        <value name="field_type">record</value>
        <value name="field_dim">0</value>
        <value name="field_opt">true</value>
        <value name="nillable">true</value>
        <array name="rec_fields" type="record" depth="1">
        </array>
      </record>
      <record javaclass="com.wm.util.Values">
        <value name="node_type">record</value>
        <value name="field_name">nsDecls</value>
        <value name="field_type">record</value>
        <value name="field_dim">0</value>
        <value name="field_opt">true</value>
        <value name="nillable">true</value>
        <array name="rec_fields" type="record" depth="1">
        </array>
      </record>
      <record javaclass="com.wm.util.Values">
        <value name="node_type">unknown</value>
        <value name="field_name">documents</value>
        <value name="field_type">string</value>
        <value name="field_dim">1</value>
        <value name="field_opt">true</value>
        <value name="nillable">true</value>
      </record>
      <record javaclass="com.wm.util.Values">
        <value name="node_type">unknown</value>
        <value name="field_name">documentTypeName</value>
        <value name="field_type">string</value>
        <value name="field_dim">0</value>
        <value name="field_opt">true</value>
        <value name="nillable">true</value>
      </record>
      <record javaclass="com.wm.util.Values">
        <value name="node_type">unknown</value>
        <value name="field_name">mixedModel</value>
        <value name="field_type">string</value>
        <value name="field_dim">0</value>
        <value name="field_opt">true</value>
        <array name="field_options" type="value" depth="1">
          <value>false</value>
          <value>true</value>
        </array>
        <value name="nillable">true</value>
      </record>
    </array>
  </record>
</Values>
</MAPTARGET>
  <MAPSOURCE>

<Values version="2.0">
  <record name="xml" javaclass="com.wm.util.Values">
    <value name="node_type">record</value>
    <value name="field_type">record</value>
    <value name="field_dim">0</value>
    <value name="nillable">true</value>
    <array name="rec_fields" type="record" depth="1">
      <record javaclass="com.wm.util.Values">
        <value name="node_type">record</value>
        <value name="node_comment"></value>
        <record name="node_hints" javaclass="com.wm.util.Values">
          <value name="field_largerEditor">false</value>
          <value name="field_password">false</value>
        </record>
        <value name="field_name">bizdoc</value>
        <value name="field_type">recref</value>
        <value name="field_dim">0</value>
        <value name="nillable">true</value>
        <value name="rec_closed">true</value>
        <value name="rec_ref">wm.tn.rec:BizDocType</value>
      </record>
      <record javaclass="com.wm.util.Values">
        <value name="node_type">unknown</value>
        <value name="field_name">node</value>
        <value name="field_type">object</value>
        <value name="field_dim">0</value>
        <value name="nillable">true</value>
      </record>
    </array>
  </record>
</Values>
</MAPSOURCE>

  <!-- nodes -->

<MAPCOPY NAME="Link" FROM="/node;3;0" TO="/node;3;0">
</MAPCOPY>
</MAP>

<MAP MODE="OUTPUT">
  <MAPTARGET>

<Values version="2.0">
  <record name="xml" javaclass="com.wm.util.Values">
    <value name="node_type">record</value>
    <value name="field_type">record</value>
    <value name="field_dim">0</value>
    <value name="nillable">true</value>
    <array name="rec_fields" type="record" depth="1">
      <record javaclass="com.wm.util.Values">
        <value name="node_type">record</value>
        <value name="node_comment"></value>
        <record name="node_hints" javaclass="com.wm.util.Values">
          <value name="field_largerEditor">false</value>
          <value name="field_password">false</value>
        </record>
        <value name="field_name">bizdoc</value>
        <value name="field_type">recref</value>
        <value name="field_dim">0</value>
        <value name="nillable">true</value>
        <value name="rec_closed">true</value>
        <value name="rec_ref">wm.tn.rec:BizDocType</value>
      </record>
      <record javaclass="com.wm.util.Values">
        <value name="node_type">unknown</value>
        <value name="field_name">node</value>
        <value name="field_type">object</value>
        <value name="field_dim">0</value>
        <value name="nillable">true</value>
      </record>
      <record javaclass="com.wm.util.Values">
        <value name="node_type">record</value>
        <value name="field_name">document</value>
        <value name="field_type">record</value>
        <value name="field_dim">0</value>
        <value name="nillable">true</value>
        <array name="rec_fields" type="record" depth="1">
          <record javaclass="com.wm.util.Values">
            <value name="node_type">record</value>
            <value name="field_name">payments</value>
            <value name="field_type">recref</value>
            <value name="field_dim">0</value>
            <value name="nillable">true</value>
            <value name="rec_ref">wm.ach.tn.sample.rec:Payments</value>
          </record>
        </array>
      </record>
      <record javaclass="com.wm.util.Values">
        <value name="node_type">record</value>
        <value name="field_name">paymentFile</value>
        <value name="field_type">recref</value>
        <value name="field_dim">0</value>
        <value name="nillable">true</value>
        <value name="rec_ref">wm.ach.tn.sample.rec:Payments</value>
      </record>
    </array>
  </record>
</Values>
</MAPTARGET>
  <MAPSOURCE>

<Values version="2.0">
  <record name="xml" javaclass="com.wm.util.Values">
    <value name="node_type">record</value>
    <value name="field_name">xmlNodeToDocumentOutput</value>
    <value name="field_type">record</value>
    <value name="field_dim">0</value>
    <value name="nillable">true</value>
    <array name="rec_fields" type="record" depth="1">
      <record javaclass="com.wm.util.Values">
        <value name="node_type">record</value>
        <value name="field_name">document</value>
        <value name="field_type">record</value>
        <value name="field_dim">0</value>
        <value name="nillable">true</value>
        <array name="rec_fields" type="record" depth="1">
          <record javaclass="com.wm.util.Values">
            <value name="node_type">record</value>
            <value name="field_name">payments</value>
            <value name="field_type">recref</value>
            <value name="field_dim">0</value>
            <value name="nillable">true</value>
            <value name="rec_ref">wm.ach.tn.sample.rec:Payments</value>
          </record>
        </array>
      </record>
    </array>
  </record>
</Values>
</MAPSOURCE>

  <!-- nodes -->

<MAPCOPY NAME="Link" FROM="/document;2;0/payments;4;0;wm.ach.tn.sample.rec:Payments" TO="/paymentFile;4;0;wm.ach.tn.sample.rec:Payments">
</MAPCOPY>

<MAPDELETE NAME="Dropper" FIELD="/document;2;0">
</MAPDELETE>

<MAPDELETE NAME="Dropper" FIELD="/node;3;0">
</MAPDELETE>
</MAP>
</INVOKE>

<INVOKE TIMEOUT="" SERVICE="wm.tn.tpa:getTPA" VALIDATE-IN="$none" VALIDATE-OUT="$none">
  <COMMENT></COMMENT>

  <!-- nodes -->

<MAP MODE="INPUT">
  <MAPTARGET>

<Values version="2.0">
  <record name="xml" javaclass="com.wm.util.Values">
    <value name="node_type">record</value>
    <value name="field_name">getTPAInput</value>
    <value name="field_type">record</value>
    <value name="field_dim">0</value>
    <value name="nillable">true</value>
    <array name="rec_fields" type="record" depth="1">
      <record javaclass="com.wm.util.Values">
        <value name="node_type">unknown</value>
        <record name="node_hints" javaclass="com.wm.util.Values">
          <value name="field_usereditable">true</value>
        </record>
        <value name="field_name">senderID</value>
        <value name="field_type">string</value>
        <value name="field_dim">0</value>
        <array name="field_options" type="value" depth="1">
          <value>Unknown</value>
        </array>
        <value name="nillable">true</value>
      </record>
      <record javaclass="com.wm.util.Values">
        <value name="node_type">unknown</value>
        <record name="node_hints" javaclass="com.wm.util.Values">
          <value name="field_usereditable">true</value>
        </record>
        <value name="field_name">receiverID</value>
        <value name="field_type">string</value>
        <value name="field_dim">0</value>
        <array name="field_options" type="value" depth="1">
          <value>Unknown</value>
        </array>
        <value name="nillable">true</value>
      </record>
      <record javaclass="com.wm.util.Values">
        <value name="node_type">unknown</value>
        <value name="field_name">agreementID</value>
        <value name="field_type">string</value>
        <value name="field_dim">0</value>
        <value name="nillable">true</value>
      </record>
      <record javaclass="com.wm.util.Values">
        <value name="node_type">unknown</value>
        <value name="field_name">direction</value>
        <value name="field_type">string</value>
        <value name="field_dim">0</value>
        <value name="field_opt">true</value>
        <array name="field_options" type="value" depth="1">
          <value>true</value>
          <value>false</value>
        </array>
        <value name="nillable">true</value>
      </record>
    </array>
  </record>
</Values>
</MAPTARGET>
  <MAPSOURCE>

<Values version="2.0">
  <record name="xml" javaclass="com.wm.util.Values">
    <value name="node_type">record</value>
    <value name="field_type">record</value>
    <value name="field_dim">0</value>
    <value name="nillable">true</value>
    <array name="rec_fields" type="record" depth="1">
    </array>
  </record>
</Values>
</MAPSOURCE>

  <!-- nodes -->

<MAPSET NAME="Setter" OVERWRITE="true" VARIABLES="false" FIELD="/agreementID;1;0">
  <DATA ENCODING="XMLValues" I18N="true">

<Values version="2.0">
  <value name="xml">CCD</value>
  <record name="type" javaclass="com.wm.util.Values">
    <value name="node_type">unknown</value>
    <value name="field_name">agreementID</value>
    <value name="field_type">string</value>
    <value name="field_dim">0</value>
    <value name="nillable">true</value>
  </record>
</Values>
</DATA>
</MAPSET>

<MAPSET NAME="Setter" OVERWRITE="true" VARIABLES="false" FIELD="/senderID;1;0">
  <DATA ENCODING="XMLValues" I18N="true">

<Values version="2.0">
  <value name="xml">Unknown</value>
  <record name="type" javaclass="com.wm.util.Values">
    <value name="node_type">unknown</value>
    <record name="node_hints" javaclass="com.wm.util.Values">
      <value name="field_usereditable">true</value>
    </record>
    <value name="field_name">senderID</value>
    <value name="field_type">string</value>
    <value name="field_dim">0</value>
    <array name="field_options" type="value" depth="1">
      <value>Unknown</value>
    </array>
    <value name="nillable">true</value>
  </record>
</Values>
</DATA>
</MAPSET>

<MAPSET NAME="Setter" OVERWRITE="true" VARIABLES="false" FIELD="/receiverID;1;0">
  <DATA ENCODING="XMLValues" I18N="true">

<Values version="2.0">
  <value name="xml">Unknown</value>
  <record name="type" javaclass="com.wm.util.Values">
    <value name="node_type">unknown</value>
    <record name="node_hints" javaclass="com.wm.util.Values">
      <value name="field_usereditable">true</value>
    </record>
    <value name="field_name">receiverID</value>
    <value name="field_type">string</value>
    <value name="field_dim">0</value>
    <array name="field_options" type="value" depth="1">
      <value>Unknown</value>
    </array>
    <value name="nillable">true</value>
  </record>
</Values>
</DATA>
</MAPSET>
</MAP>

<MAP MODE="OUTPUT">
  <MAPTARGET>

<Values version="2.0">
  <record name="xml" javaclass="com.wm.util.Values">
    <value name="node_type">record</value>
    <value name="field_type">record</value>
    <value name="field_dim">0</value>
    <value name="nillable">true</value>
    <array name="rec_fields" type="record" depth="1">
      <record javaclass="com.wm.util.Values">
        <value name="node_type">unknown</value>
        <value name="field_name">senderID</value>
        <value name="field_type">string</value>
        <value name="field_dim">0</value>
        <value name="nillable">true</value>
      </record>
      <record javaclass="com.wm.util.Values">
        <value name="node_type">unknown</value>
        <value name="field_name">receiverID</value>
        <value name="field_type">string</value>
        <value name="field_dim">0</value>
        <value name="nillable">true</value>
      </record>
      <record javaclass="com.wm.util.Values">
        <value name="node_type">record</value>
        <value name="field_name">tpaData</value>
        <value name="field_type">recref</value>
        <value name="field_dim">0</value>
        <value name="nillable">true</value>
        <value name="rec_ref">wm.ach.tn.rec:TPA</value>
      </record>
      <record javaclass="com.wm.util.Values">
        <value name="node_type">unknown</value>
        <value name="field_name">agreementID</value>
        <value name="field_type">string</value>
        <value name="field_dim">0</value>
        <value name="nillable">true</value>
      </record>
      <record javaclass="com.wm.util.Values">
        <value name="node_type">record</value>
        <value name="node_comment"></value>
        <record name="node_hints" javaclass="com.wm.util.Values">
          <value name="field_largerEditor">false</value>
          <value name="field_password">false</value>
        </record>
        <value name="field_name">bizdoc</value>
        <value name="field_type">recref</value>
        <value name="field_dim">0</value>
        <value name="nillable">true</value>
        <value name="rec_closed">true</value>
        <value name="rec_ref">wm.tn.rec:BizDocType</value>
      </record>
      <record javaclass="com.wm.util.Values">
        <value name="node_type">record</value>
        <value name="field_name">paymentFile</value>
        <value name="field_type">recref</value>
        <value name="field_dim">0</value>
        <value name="nillable">true</value>
        <value name="rec_ref">wm.ach.tn.sample.rec:Payments</value>
      </record>
      <record javaclass="com.wm.util.Values">
        <value name="node_type">record</value>
        <value name="field_name">tpa</value>
        <value name="field_type">recref</value>
        <value name="field_dim">0</value>
        <value name="nillable">true</value>
        <value name="rec_ref">wm.tn.rec:TPA</value>
      </record>
      <record javaclass="com.wm.util.Values">
        <value name="node_type">record</value>
        <value name="field_name">error</value>
        <value name="field_type">recref</value>
        <value name="field_dim">0</value>
        <value name="field_opt">true</value>
        <value name="nillable">true</value>
        <value name="rec_ref">wm.tn.rec:TpaError</value>
      </record>
    </array>
  </record>
</Values>
</MAPTARGET>
  <MAPSOURCE>

<Values version="2.0">
  <record name="xml" javaclass="com.wm.util.Values">
    <value name="node_type">record</value>
    <value name="field_name">getTPAOutput</value>
    <value name="field_type">record</value>
    <value name="field_dim">0</value>
    <value name="nillable">true</value>
    <array name="rec_fields" type="record" depth="1">
      <record javaclass="com.wm.util.Values">
        <value name="node_type">record</value>
        <value name="field_name">tpa</value>
        <value name="field_type">recref</value>
        <value name="field_dim">0</value>
        <value name="nillable">true</value>
        <value name="rec_ref">wm.tn.rec:TPA</value>
      </record>
      <record javaclass="com.wm.util.Values">
        <value name="node_type">record</value>
        <value name="field_name">error</value>
        <value name="field_type">recref</value>
        <value name="field_dim">0</value>
        <value name="field_opt">true</value>
        <value name="nillable">true</value>
        <value name="rec_ref">wm.tn.rec:TpaError</value>
      </record>
    </array>
  </record>
</Values>
</MAPSOURCE>

  <!-- nodes -->

<MAPCOPY NAME="Link" FROM="/tpa;4;0;wm.tn.rec:TPA/tpaData;2;0" TO="/tpaData;4;0;wm.ach.tn.rec:TPA">
</MAPCOPY>

<MAPDELETE NAME="Dropper" FIELD="/tpa;4;0;wm.tn.rec:TPA">
</MAPDELETE>

<MAPDELETE NAME="Dropper" FIELD="/agreementID;1;0">
</MAPDELETE>

<MAPDELETE NAME="Dropper" FIELD="/senderID;1;0">
</MAPDELETE>

<MAPDELETE NAME="Dropper" FIELD="/receiverID;1;0">
</MAPDELETE>
</MAP>
</INVOKE>

<MAP MODE="STANDALONE">
  <COMMENT>get BatchHeader</COMMENT>
  <MAPTARGET>

<Values version="2.0">
  <record name="xml" javaclass="com.wm.util.Values">
    <value name="node_type">record</value>
    <value name="field_type">record</value>
    <value name="field_dim">0</value>
    <value name="nillable">true</value>
    <array name="rec_fields" type="record" depth="1">
      <record javaclass="com.wm.util.Values">
        <value name="node_type">record</value>
        <value name="field_name">tpaData</value>
        <value name="field_type">recref</value>
        <value name="field_dim">0</value>
        <value name="nillable">true</value>
        <value name="rec_ref">wm.ach.tn.rec:TPA</value>
      </record>
      <record javaclass="com.wm.util.Values">
        <value name="node_type">record</value>
        <value name="node_comment"></value>
        <record name="node_hints" javaclass="com.wm.util.Values">
          <value name="field_largerEditor">false</value>
          <value name="field_password">false</value>
        </record>
        <value name="field_name">bizdoc</value>
        <value name="field_type">recref</value>
        <value name="field_dim">0</value>
        <value name="nillable">true</value>
        <value name="rec_closed">true</value>
        <value name="rec_ref">wm.tn.rec:BizDocType</value>
      </record>
      <record javaclass="com.wm.util.Values">
        <value name="node_type">record</value>
        <value name="field_name">batchHeader</value>
        <value name="field_type">record</value>
        <value name="field_dim">0</value>
        <value name="nillable">true</value>
        <array name="rec_fields" type="record" depth="1">
        </array>
      </record>
      <record javaclass="com.wm.util.Values">
        <value name="node_type">record</value>
        <value name="field_name">paymentFile</value>
        <value name="field_type">recref</value>
        <value name="field_dim">0</value>
        <value name="nillable">true</value>
        <value name="rec_ref">wm.ach.tn.sample.rec:Payments</value>
      </record>
      <record javaclass="com.wm.util.Values">
        <value name="node_type">record</value>
        <value name="field_name">error</value>
        <value name="field_type">recref</value>
        <value name="field_dim">0</value>
        <value name="field_opt">true</value>
        <value name="nillable">true</value>
        <value name="rec_ref">wm.tn.rec:TpaError</value>
      </record>
    </array>
  </record>
</Values>
</MAPTARGET>
  <MAPSOURCE>

<Values version="2.0">
  <record name="xml" javaclass="com.wm.util.Values">
    <value name="node_type">record</value>
    <value name="field_type">record</value>
    <value name="field_dim">0</value>
    <value name="nillable">true</value>
    <array name="rec_fields" type="record" depth="1">
      <record javaclass="com.wm.util.Values">
        <value name="node_type">record</value>
        <value name="field_name">tpaData</value>
        <value name="field_type">recref</value>
        <value name="field_dim">0</value>
        <value name="nillable">true</value>
        <value name="rec_ref">wm.ach.tn.rec:TPA</value>
      </record>
      <record javaclass="com.wm.util.Values">
        <value name="node_type">record</value>
        <value name="node_comment"></value>
        <record name="node_hints" javaclass="com.wm.util.Values">
          <value name="field_largerEditor">false</value>
          <value name="field_password">false</value>
        </record>
        <value name="field_name">bizdoc</value>
        <value name="field_type">recref</value>
        <value name="field_dim">0</value>
        <value name="nillable">true</value>
        <value name="rec_closed">true</value>
        <value name="rec_ref">wm.tn.rec:BizDocType</value>
      </record>
      <record javaclass="com.wm.util.Values">
        <value name="node_type">record</value>
        <value name="field_name">paymentFile</value>
        <value name="field_type">recref</value>
        <value name="field_dim">0</value>
        <value name="nillable">true</value>
        <value name="rec_ref">wm.ach.tn.sample.rec:Payments</value>
      </record>
      <record javaclass="com.wm.util.Values">
        <value name="node_type">record</value>
        <value name="field_name">error</value>
        <value name="field_type">recref</value>
        <value name="field_dim">0</value>
        <value name="field_opt">true</value>
        <value name="nillable">true</value>
        <value name="rec_ref">wm.tn.rec:TpaError</value>
      </record>
    </array>
  </record>
</Values>
</MAPSOURCE>

  <!-- nodes -->

<MAPCOPY NAME="Link" FROM="/tpaData;4;0;wm.ach.tn.rec:TPA/Batch Header;4;0;wm.ach.record:ALL_ENTRIES_BATCH_HEADER" TO="/batchHeader;2;0">
</MAPCOPY>
</MAP>

<MAP MODE="STANDALONE">
  <COMMENT>Map EffectiveDate</COMMENT>
  <MAPTARGET>

<Values version="2.0">
  <record name="xml" javaclass="com.wm.util.Values">
    <value name="node_type">record</value>
    <value name="field_type">record</value>
    <value name="field_dim">0</value>
    <value name="nillable">true</value>
    <array name="rec_fields" type="record" depth="1">
      <record javaclass="com.wm.util.Values">
        <value name="node_type">record</value>
        <value name="field_name">tpaData</value>
        <value name="field_type">recref</value>
        <value name="field_dim">0</value>
        <value name="nillable">true</value>
        <value name="rec_ref">wm.ach.tn.rec:TPA</value>
      </record>
      <record javaclass="com.wm.util.Values">
        <value name="node_type">record</value>
        <value name="node_comment"></value>
        <record name="node_hints" javaclass="com.wm.util.Values">
          <value name="field_largerEditor">false</value>
          <value name="field_password">false</value>
        </record>
        <value name="field_name">bizdoc</value>
        <value name="field_type">recref</value>
        <value name="field_dim">0</value>
        <value name="nillable">true</value>
        <value name="rec_closed">true</value>
        <value name="rec_ref">wm.tn.rec:BizDocType</value>
      </record>
      <record javaclass="com.wm.util.Values">
        <value name="node_type">record</value>
        <value name="field_name">batchHeader</value>
        <value name="field_type">record</value>
        <value name="field_dim">0</value>
        <value name="nillable">true</value>
        <array name="rec_fields" type="record" depth="1">
          <record javaclass="com.wm.util.Values">
            <value name="node_type">unknown</value>
            <value name="field_name">EFFECTIVE_ENTRY_DATE</value>
            <value name="field_type">string</value>
            <value name="field_dim">0</value>
            <value name="nillable">true</value>
          </record>
        </array>
      </record>
      <record javaclass="com.wm.util.Values">
        <value name="node_type">record</value>
        <value name="field_name">paymentFile</value>
        <value name="field_type">recref</value>
        <value name="field_dim">0</value>
        <value name="nillable">true</value>
        <value name="rec_ref">wm.ach.tn.sample.rec:Payments</value>
      </record>
      <record javaclass="com.wm.util.Values">
        <value name="node_type">record</value>
        <value name="field_name">error</value>
        <value name="field_type">recref</value>
        <value name="field_dim">0</value>
        <value name="field_opt">true</value>
        <value name="nillable">true</value>
        <value name="rec_ref">wm.tn.rec:TpaError</value>
      </record>
    </array>
  </record>
</Values>
</MAPTARGET>
  <MAPSOURCE>

<Values version="2.0">
  <record name="xml" javaclass="com.wm.util.Values">
    <value name="node_type">record</value>
    <value name="field_type">record</value>
    <value name="field_dim">0</value>
    <value name="nillable">true</value>
    <array name="rec_fields" type="record" depth="1">
      <record javaclass="com.wm.util.Values">
        <value name="node_type">record</value>
        <value name="field_name">tpaData</value>
        <value name="field_type">recref</value>
        <value name="field_dim">0</value>
        <value name="nillable">true</value>
        <value name="rec_ref">wm.ach.tn.rec:TPA</value>
      </record>
      <record javaclass="com.wm.util.Values">
        <value name="node_type">record</value>
        <value name="node_comment"></value>
        <record name="node_hints" javaclass="com.wm.util.Values">
          <value name="field_largerEditor">false</value>
          <value name="field_password">false</value>
        </record>
        <value name="field_name">bizdoc</value>
        <value name="field_type">recref</value>
        <value name="field_dim">0</value>
        <value name="nillable">true</value>
        <value name="rec_closed">true</value>
        <value name="rec_ref">wm.tn.rec:BizDocType</value>
      </record>
      <record javaclass="com.wm.util.Values">
        <value name="node_type">record</value>
        <value name="field_name">batchHeader</value>
        <value name="field_type">record</value>
        <value name="field_dim">0</value>
        <value name="nillable">true</value>
        <array name="rec_fields" type="record" depth="1">
        </array>
      </record>
      <record javaclass="com.wm.util.Values">
        <value name="node_type">record</value>
        <value name="field_name">paymentFile</value>
        <value name="field_type">recref</value>
        <value name="field_dim">0</value>
        <value name="nillable">true</value>
        <value name="rec_ref">wm.ach.tn.sample.rec:Payments</value>
      </record>
      <record javaclass="com.wm.util.Values">
        <value name="node_type">record</value>
        <value name="field_name">error</value>
        <value name="field_type">recref</value>
        <value name="field_dim">0</value>
        <value name="field_opt">true</value>
        <value name="nillable">true</value>
        <value name="rec_ref">wm.tn.rec:TpaError</value>
      </record>
    </array>
  </record>
</Values>
</MAPSOURCE>

  <!-- nodes -->

<MAPCOPY NAME="Link" FROM="/paymentFile;4;0;wm.ach.tn.sample.rec:Payments/EffectiveDate;1;0" TO="/batchHeader;2;0/EFFECTIVE_ENTRY_DATE;1;0">
</MAPCOPY>
</MAP>

<INVOKE TIMEOUT="" SERVICE="wm.ach.batch:createBatch" VALIDATE-IN="$none" VALIDATE-OUT="$none">
  <COMMENT>A Batch Object must be created before appending entries</COMMENT>

  <!-- nodes -->

<MAP MODE="INPUT">
  <MAPTARGET>

<Values version="2.0">
  <record name="xml" javaclass="com.wm.util.Values">
    <value name="node_type">record</value>
    <value name="field_name">createBatchInput</value>
    <value name="field_type">record</value>
    <value name="field_dim">0</value>
    <value name="nillable">true</value>
    <array name="rec_fields" type="record" depth="1">
      <record javaclass="com.wm.util.Values">
        <value name="node_type">record</value>
        <value name="field_name">batchHeader</value>
        <value name="field_type">record</value>
        <value name="field_dim">0</value>
        <value name="nillable">true</value>
        <array name="rec_fields" type="record" depth="1">
        </array>
      </record>
    </array>
  </record>
</Values>
</MAPTARGET>
  <MAPSOURCE>

<Values version="2.0">
  <record name="xml" javaclass="com.wm.util.Values">
    <value name="node_type">record</value>
    <value name="field_type">record</value>
    <value name="field_dim">0</value>
    <value name="nillable">true</value>
    <array name="rec_fields" type="record" depth="1">
      <record javaclass="com.wm.util.Values">
        <value name="node_type">record</value>
        <value name="field_name">tpaData</value>
        <value name="field_type">recref</value>
        <value name="field_dim">0</value>
        <value name="nillable">true</value>
        <value name="rec_ref">wm.ach.tn.rec:TPA</value>
      </record>
      <record javaclass="com.wm.util.Values">
        <value name="node_type">record</value>
        <value name="node_comment"></value>
        <record name="node_hints" javaclass="com.wm.util.Values">
          <value name="field_largerEditor">false</value>
          <value name="field_password">false</value>
        </record>
        <value name="field_name">bizdoc</value>
        <value name="field_type">recref</value>
        <value name="field_dim">0</value>
        <value name="nillable">true</value>
        <value name="rec_closed">true</value>
        <value name="rec_ref">wm.tn.rec:BizDocType</value>
      </record>
      <record javaclass="com.wm.util.Values">
        <value name="node_type">record</value>
        <value name="field_name">batchHeader</value>
        <value name="field_type">record</value>
        <value name="field_dim">0</value>
        <value name="nillable">true</value>
        <array name="rec_fields" type="record" depth="1">
          <record javaclass="com.wm.util.Values">
            <value name="node_type">unknown</value>
            <value name="field_name">EFFECTIVE_ENTRY_DATE</value>
            <value name="field_type">string</value>
            <value name="field_dim">0</value>
            <value name="nillable">true</value>
          </record>
        </array>
      </record>
      <record javaclass="com.wm.util.Values">
        <value name="node_type">record</value>
        <value name="field_name">paymentFile</value>
        <value name="field_type">recref</value>
        <value name="field_dim">0</value>
        <value name="nillable">true</value>
        <value name="rec_ref">wm.ach.tn.sample.rec:Payments</value>
      </record>
      <record javaclass="com.wm.util.Values">
        <value name="node_type">record</value>
        <value name="field_name">error</value>
        <value name="field_type">recref</value>
        <value name="field_dim">0</value>
        <value name="field_opt">true</value>
        <value name="nillable">true</value>
        <value name="rec_ref">wm.tn.rec:TpaError</value>
      </record>
    </array>
  </record>
</Values>
</MAPSOURCE>

  <!-- nodes -->

<MAPCOPY NAME="Link" FROM="/batchHeader;2;0" TO="/batchHeader;2;0">
</MAPCOPY>
</MAP>

<MAP MODE="OUTPUT">
</MAP>
</INVOKE>

<LOOP TIMEOUT="" IN-ARRAY="/paymentFile/PaymentList">
  <COMMENT></COMMENT>

  <!-- nodes -->

<MAP MODE="STANDALONE">
  <COMMENT></COMMENT>
  <MAPTARGET>

<Values version="2.0">
  <record name="xml" javaclass="com.wm.util.Values">
    <value name="node_type">record</value>
    <value name="field_type">record</value>
    <value name="field_dim">0</value>
    <value name="nillable">true</value>
    <array name="rec_fields" type="record" depth="1">
      <record javaclass="com.wm.util.Values">
        <value name="node_type">record</value>
        <value name="field_name">tpaData</value>
        <value name="field_type">recref</value>
        <value name="field_dim">0</value>
        <value name="nillable">true</value>
        <value name="rec_ref">wm.ach.tn.rec:TPA</value>
      </record>
      <record javaclass="com.wm.util.Values">
        <value name="node_type">record</value>
        <value name="node_comment"></value>
        <record name="node_hints" javaclass="com.wm.util.Values">
          <value name="field_largerEditor">false</value>
          <value name="field_password">false</value>
        </record>
        <value name="field_name">bizdoc</value>
        <value name="field_type">recref</value>
        <value name="field_dim">0</value>
        <value name="nillable">true</value>
        <value name="rec_closed">true</value>
        <value name="rec_ref">wm.tn.rec:BizDocType</value>
      </record>
      <record javaclass="com.wm.util.Values">
        <value name="node_type">record</value>
        <value name="field_name">batchHeader</value>
        <value name="field_type">record</value>
        <value name="field_dim">0</value>
        <value name="nillable">true</value>
        <array name="rec_fields" type="record" depth="1">
        </array>
      </record>
      <record javaclass="com.wm.util.Values">
        <value name="node_type">record</value>
        <value name="field_name">paymentFile</value>
        <value name="field_type">recref</value>
        <value name="field_dim">0</value>
        <value name="nillable">true</value>
        <value name="rec_ref">wm.ach.tn.sample.rec:Payments</value>
      </record>
      <record javaclass="com.wm.util.Values">
        <value name="node_type">record</value>
        <value name="field_name">error</value>
        <value name="field_type">recref</value>
        <value name="field_dim">0</value>
        <value name="field_opt">true</value>
        <value name="nillable">true</value>
        <value name="rec_ref">wm.tn.rec:TpaError</value>
      </record>
      <record javaclass="com.wm.util.Values">
        <value name="node_type">record</value>
        <value name="field_name">ccdEntry</value>
        <value name="field_type">recref</value>
        <value name="field_dim">0</value>
        <value name="nillable">true</value>
        <value name="rec_ref">wm.ach.record:CCD_ENTRY_DETAIL</value>
      </record>
      <record javaclass="com.wm.util.Values">
        <value name="node_type">unknown</value>
        <value name="field_name">batchObject</value>
        <value name="field_type">object</value>
        <value name="field_dim">0</value>
        <value name="nillable">true</value>
      </record>
    </array>
  </record>
</Values>
</MAPTARGET>
  <MAPSOURCE>

<Values version="2.0">
  <record name="xml" javaclass="com.wm.util.Values">
    <value name="node_type">record</value>
    <value name="field_type">record</value>
    <value name="field_dim">0</value>
    <value name="nillable">true</value>
    <array name="rec_fields" type="record" depth="1">
      <record javaclass="com.wm.util.Values">
        <value name="node_type">record</value>
        <value name="field_name">tpaData</value>
        <value name="field_type">recref</value>
        <value name="field_dim">0</value>
        <value name="nillable">true</value>
        <value name="rec_ref">wm.ach.tn.rec:TPA</value>
      </record>
      <record javaclass="com.wm.util.Values">
        <value name="node_type">record</value>
        <value name="node_comment"></value>
        <record name="node_hints" javaclass="com.wm.util.Values">
          <value name="field_largerEditor">false</value>
          <value name="field_password">false</value>
        </record>
        <value name="field_name">bizdoc</value>
        <value name="field_type">recref</value>
        <value name="field_dim">0</value>
        <value name="nillable">true</value>
        <value name="rec_closed">true</value>
        <value name="rec_ref">wm.tn.rec:BizDocType</value>
      </record>
      <record javaclass="com.wm.util.Values">
        <value name="node_type">record</value>
        <value name="field_name">batchHeader</value>
        <value name="field_type">record</value>
        <value name="field_dim">0</value>
        <value name="nillable">true</value>
        <array name="rec_fields" type="record" depth="1">
        </array>
      </record>
      <record javaclass="com.wm.util.Values">
        <value name="node_type">record</value>
        <value name="field_name">paymentFile</value>
        <value name="field_type">recref</value>
        <value name="field_dim">0</value>
        <value name="nillable">true</value>
        <value name="rec_ref">wm.ach.tn.sample.rec:Payments</value>
      </record>
      <record javaclass="com.wm.util.Values">
        <value name="node_type">record</value>
        <value name="field_name">error</value>
        <value name="field_type">recref</value>
        <value name="field_dim">0</value>
        <value name="field_opt">true</value>
        <value name="nillable">true</value>
        <value name="rec_ref">wm.tn.rec:TpaError</value>
      </record>
      <record javaclass="com.wm.util.Values">
        <value name="node_type">unknown</value>
        <value name="field_name">batchObject</value>
        <value name="field_type">object</value>
        <value name="field_dim">0</value>
        <value name="nillable">true</value>
      </record>
      <record javaclass="com.wm.util.Values">
        <value name="node_type">unknown</value>
        <value name="field_name">$iteration</value>
        <value name="field_type">string</value>
        <value name="field_dim">0</value>
        <value name="nillable">true</value>
      </record>
    </array>
  </record>
</Values>
</MAPSOURCE>

  <!-- nodes -->

<MAPINVOKE SERVICE="pub.string:replace" VALIDATE-IN="$none" VALIDATE-OUT="$none" INVOKE-ORDER="0">

  <!-- nodes -->

<MAP MODE="INVOKEINPUT">

  <!-- nodes -->

<MAPSET NAME="Setter" OVERWRITE="true" VARIABLES="false" FIELD="/searchString;1;0">
  <DATA ENCODING="XMLValues" I18N="true">

<Values version="2.0">
  <value name="xml">.</value>
  <record name="type" javaclass="com.wm.util.Values">
    <value name="node_type">unknown</value>
    <value name="field_name">searchString</value>
    <value name="field_type">string</value>
    <value name="field_dim">0</value>
    <value name="nillable">true</value>
  </record>
</Values>
</DATA>
</MAPSET>

<MAPSET NAME="Setter" OVERWRITE="true" VARIABLES="false" FIELD="/replaceString;1;0">
  <DATA ENCODING="XMLValues" I18N="true">

<Values version="2.0">
  <value name="xml"></value>
  <record name="type" javaclass="com.wm.util.Values">
    <value name="node_type">unknown</value>
    <value name="field_name">replaceString</value>
    <value name="field_type">string</value>
    <value name="field_dim">0</value>
    <value name="nillable">true</value>
  </record>
</Values>
</DATA>
</MAPSET>

<MAPCOPY NAME="Link" FROM="/paymentFile;4;0;wm.ach.tn.sample.rec:Payments/PaymentList;2;0/Amount;1;0" TO="/inString;1;0">
</MAPCOPY>
</MAP>

<MAP MODE="INVOKEOUTPUT">

  <!-- nodes -->

<MAPCOPY NAME="Link" FROM="/value;1;0" TO="/ccdEntry;4;0;wm.ach.record:CCD_ENTRY_DETAIL/AMOUNT;1;0">
</MAPCOPY>
</MAP>
</MAPINVOKE>

<MAPINVOKE SERVICE="pub.string:substring" VALIDATE-IN="$none" VALIDATE-OUT="$none" INVOKE-ORDER="0">

  <!-- nodes -->

<MAP MODE="INVOKEINPUT">

  <!-- nodes -->

<MAPCOPY NAME="Link" FROM="/paymentFile;4;0;wm.ach.tn.sample.rec:Payments/PaymentList;2;0/RTIdentification;1;0" TO="/inString;1;0">
</MAPCOPY>

<MAPSET NAME="Setter" OVERWRITE="true" VARIABLES="false" FIELD="/beginIndex;1;0">
  <DATA ENCODING="XMLValues" I18N="true">

<Values version="2.0">
  <value name="xml">0</value>
  <record name="type" javaclass="com.wm.util.Values">
    <value name="node_type">unknown</value>
    <value name="field_name">beginIndex</value>
    <value name="field_type">string</value>
    <value name="field_dim">0</value>
    <value name="nillable">true</value>
  </record>
</Values>
</DATA>
</MAPSET>

<MAPSET NAME="Setter" OVERWRITE="true" VARIABLES="false" FIELD="/endIndex;1;0">
  <DATA ENCODING="XMLValues" I18N="true">

<Values version="2.0">
  <value name="xml">8</value>
  <record name="type" javaclass="com.wm.util.Values">
    <value name="node_type">unknown</value>
    <value name="field_name">endIndex</value>
    <value name="field_type">string</value>
    <value name="field_dim">0</value>
    <value name="nillable">true</value>
  </record>
</Values>
</DATA>
</MAPSET>
</MAP>

<MAP MODE="INVOKEOUTPUT">

  <!-- nodes -->

<MAPCOPY NAME="Link" FROM="/value;1;0" TO="/ccdEntry;4;0;wm.ach.record:CCD_ENTRY_DETAIL/RECEIVING_DFI_IDENTIFICATION;1;0">
</MAPCOPY>
</MAP>
</MAPINVOKE>

<MAPINVOKE SERVICE="pub.string:substring" VALIDATE-IN="$none" VALIDATE-OUT="$none" INVOKE-ORDER="0">

  <!-- nodes -->

<MAP MODE="INVOKEINPUT">

  <!-- nodes -->

<MAPCOPY NAME="Link" FROM="/paymentFile;4;0;wm.ach.tn.sample.rec:Payments/PaymentList;2;0/RTIdentification;1;0" TO="/inString;1;0">
</MAPCOPY>

<MAPSET NAME="Setter" OVERWRITE="true" VARIABLES="false" FIELD="/beginIndex;1;0">
  <DATA ENCODING="XMLValues" I18N="true">

<Values version="2.0">
  <value name="xml">8</value>
  <record name="type" javaclass="com.wm.util.Values">
    <value name="node_type">unknown</value>
    <value name="field_name">beginIndex</value>
    <value name="field_type">string</value>
    <value name="field_dim">0</value>
    <value name="nillable">true</value>
  </record>
</Values>
</DATA>
</MAPSET>

<MAPSET NAME="Setter" OVERWRITE="true" VARIABLES="false" FIELD="/endIndex;1;0">
  <DATA ENCODING="XMLValues" I18N="true">

<Values version="2.0">
  <value name="xml">9</value>
  <record name="type" javaclass="com.wm.util.Values">
    <value name="node_type">unknown</value>
    <value name="field_name">endIndex</value>
    <value name="field_type">string</value>
    <value name="field_dim">0</value>
    <value name="nillable">true</value>
  </record>
</Values>
</DATA>
</MAPSET>
</MAP>

<MAP MODE="INVOKEOUTPUT">

  <!-- nodes -->

<MAPCOPY NAME="Link" FROM="/value;1;0" TO="/ccdEntry;4;0;wm.ach.record:CCD_ENTRY_DETAIL/CHECK_DIGIT;1;0">
</MAPCOPY>
</MAP>
</MAPINVOKE>

<MAPCOPY NAME="Link" FROM="/paymentFile;4;0;wm.ach.tn.sample.rec:Payments/PaymentList;2;0/AccountNumber;1;0" TO="/ccdEntry;4;0;wm.ach.record:CCD_ENTRY_DETAIL/DFI_ACCOUNT_NUMBER;1;0">
</MAPCOPY>

<MAPSET NAME="Setter" OVERWRITE="true" VARIABLES="false" FIELD="/ccdEntry;4;0;wm.ach.record:CCD_ENTRY_DETAIL/RECORD_TYPE_CODE;1;0">
  <DATA ENCODING="XMLValues" I18N="true">

<Values version="2.0">
  <value name="xml">6</value>
  <record name="type" javaclass="com.wm.util.Values">
    <value name="node_type">unknown</value>
    <value name="field_name">RECORD_TYPE_CODE</value>
    <value name="field_type">string</value>
    <value name="field_dim">0</value>
    <value name="nillable">true</value>
  </record>
</Values>
</DATA>
</MAPSET>

<MAPSET NAME="Setter" OVERWRITE="true" VARIABLES="false" FIELD="/ccdEntry;4;0;wm.ach.record:CCD_ENTRY_DETAIL/TRANSACTION_CODE;1;0">
  <DATA ENCODING="XMLValues" I18N="true">

<Values version="2.0">
  <value name="xml">22</value>
  <record name="type" javaclass="com.wm.util.Values">
    <value name="node_type">unknown</value>
    <value name="field_name">TRANSACTION_CODE</value>
    <value name="field_type">string</value>
    <value name="field_dim">0</value>
    <value name="nillable">true</value>
  </record>
</Values>
</DATA>
</MAPSET>

<MAPSET NAME="Setter" OVERWRITE="true" VARIABLES="false" FIELD="/ccdEntry;4;0;wm.ach.record:CCD_ENTRY_DETAIL/ADDENDA_RECORD_INDICATOR;1;0">
  <DATA ENCODING="XMLValues" I18N="true">

<Values version="2.0">
  <value name="xml">0</value>
  <record name="type" javaclass="com.wm.util.Values">
    <value name="node_type">unknown</value>
    <value name="field_name">ADDENDA_RECORD_INDICATOR</value>
    <value name="field_type">string</value>
    <value name="field_dim">0</value>
    <value name="nillable">true</value>
  </record>
</Values>
</DATA>
</MAPSET>
</MAP>

<INVOKE TIMEOUT="" SERVICE="wm.ach.batch:appendEntry" VALIDATE-IN="$none" VALIDATE-OUT="$none">
  <COMMENT></COMMENT>

  <!-- nodes -->

<MAP MODE="INPUT">
  <MAPTARGET>

<Values version="2.0">
  <record name="xml" javaclass="com.wm.util.Values">
    <value name="node_type">record</value>
    <value name="field_name">appendEntryInput</value>
    <value name="field_type">record</value>
    <value name="field_dim">0</value>
    <value name="nillable">true</value>
    <array name="rec_fields" type="record" depth="1">
      <record javaclass="com.wm.util.Values">
        <value name="node_type">record</value>
        <value name="field_name">entry</value>
        <value name="field_type">record</value>
        <value name="field_dim">0</value>
        <value name="nillable">true</value>
        <array name="rec_fields" type="record" depth="1">
        </array>
      </record>
      <record javaclass="com.wm.util.Values">
        <value name="node_type">record</value>
        <value name="field_name">addendas</value>
        <value name="field_type">record</value>
        <value name="field_dim">1</value>
        <value name="nillable">true</value>
        <array name="rec_fields" type="record" depth="1">
        </array>
      </record>
      <record javaclass="com.wm.util.Values">
        <value name="node_type">unknown</value>
        <value name="field_name">batchObject</value>
        <value name="field_type">object</value>
        <value name="field_dim">0</value>
        <value name="nillable">true</value>
      </record>
    </array>
  </record>
</Values>
</MAPTARGET>
  <MAPSOURCE>

<Values version="2.0">
  <record name="xml" javaclass="com.wm.util.Values">
    <value name="node_type">record</value>
    <value name="field_type">record</value>
    <value name="field_dim">0</value>
    <value name="nillable">true</value>
    <array name="rec_fields" type="record" depth="1">
      <record javaclass="com.wm.util.Values">
        <value name="node_type">record</value>
        <value name="field_name">tpaData</value>
        <value name="field_type">recref</value>
        <value name="field_dim">0</value>
        <value name="nillable">true</value>
        <value name="rec_ref">wm.ach.tn.rec:TPA</value>
      </record>
      <record javaclass="com.wm.util.Values">
        <value name="node_type">record</value>
        <value name="node_comment"></value>
        <record name="node_hints" javaclass="com.wm.util.Values">
          <value name="field_largerEditor">false</value>
          <value name="field_password">false</value>
        </record>
        <value name="field_name">bizdoc</value>
        <value name="field_type">recref</value>
        <value name="field_dim">0</value>
        <value name="nillable">true</value>
        <value name="rec_closed">true</value>
        <value name="rec_ref">wm.tn.rec:BizDocType</value>
      </record>
      <record javaclass="com.wm.util.Values">
        <value name="node_type">record</value>
        <value name="field_name">batchHeader</value>
        <value name="field_type">record</value>
        <value name="field_dim">0</value>
        <value name="nillable">true</value>
        <array name="rec_fields" type="record" depth="1">
        </array>
      </record>
      <record javaclass="com.wm.util.Values">
        <value name="node_type">record</value>
        <value name="field_name">paymentFile</value>
        <value name="field_type">recref</value>
        <value name="field_dim">0</value>
        <value name="nillable">true</value>
        <value name="rec_ref">wm.ach.tn.sample.rec:Payments</value>
      </record>
      <record javaclass="com.wm.util.Values">
        <value name="node_type">record</value>
        <value name="field_name">error</value>
        <value name="field_type">recref</value>
        <value name="field_dim">0</value>
        <value name="field_opt">true</value>
        <value name="nillable">true</value>
        <value name="rec_ref">wm.tn.rec:TpaError</value>
      </record>
      <record javaclass="com.wm.util.Values">
        <value name="node_type">record</value>
        <value name="field_name">ccdEntry</value>
        <value name="field_type">recref</value>
        <value name="field_dim">0</value>
        <value name="nillable">true</value>
        <value name="rec_ref">wm.ach.record:CCD_ENTRY_DETAIL</value>
      </record>
      <record javaclass="com.wm.util.Values">
        <value name="node_type">unknown</value>
        <value name="field_name">batchObject</value>
        <value name="field_type">object</value>
        <value name="field_dim">0</value>
        <value name="nillable">true</value>
      </record>
      <record javaclass="com.wm.util.Values">
        <value name="node_type">unknown</value>
        <value name="field_name">$iteration</value>
        <value name="field_type">string</value>
        <value name="field_dim">0</value>
        <value name="nillable">true</value>
      </record>
    </array>
  </record>
</Values>
</MAPSOURCE>

  <!-- nodes -->

<MAPCOPY NAME="Link" FROM="/ccdEntry;4;0;wm.ach.record:CCD_ENTRY_DETAIL" TO="/entry;2;0">
</MAPCOPY>
</MAP>

<MAP MODE="OUTPUT">
  <MAPTARGET>

<Values version="2.0">
  <record name="xml" javaclass="com.wm.util.Values">
    <value name="node_type">record</value>
    <value name="field_type">record</value>
    <value name="field_dim">0</value>
    <value name="nillable">true</value>
    <array name="rec_fields" type="record" depth="1">
      <record javaclass="com.wm.util.Values">
        <value name="node_type">record</value>
        <value name="field_name">entry</value>
        <value name="field_type">record</value>
        <value name="field_dim">0</value>
        <value name="nillable">true</value>
        <array name="rec_fields" type="record" depth="1">
        </array>
      </record>
      <record javaclass="com.wm.util.Values">
        <value name="node_type">record</value>
        <value name="field_name">tpaData</value>
        <value name="field_type">recref</value>
        <value name="field_dim">0</value>
        <value name="nillable">true</value>
        <value name="rec_ref">wm.ach.tn.rec:TPA</value>
      </record>
      <record javaclass="com.wm.util.Values">
        <value name="node_type">record</value>
        <value name="node_comment"></value>
        <record name="node_hints" javaclass="com.wm.util.Values">
          <value name="field_largerEditor">false</value>
          <value name="field_password">false</value>
        </record>
        <value name="field_name">bizdoc</value>
        <value name="field_type">recref</value>
        <value name="field_dim">0</value>
        <value name="nillable">true</value>
        <value name="rec_closed">true</value>
        <value name="rec_ref">wm.tn.rec:BizDocType</value>
      </record>
      <record javaclass="com.wm.util.Values">
        <value name="node_type">record</value>
        <value name="field_name">batchHeader</value>
        <value name="field_type">record</value>
        <value name="field_dim">0</value>
        <value name="nillable">true</value>
        <array name="rec_fields" type="record" depth="1">
        </array>
      </record>
      <record javaclass="com.wm.util.Values">
        <value name="node_type">record</value>
        <value name="field_name">paymentFile</value>
        <value name="field_type">recref</value>
        <value name="field_dim">0</value>
        <value name="nillable">true</value>
        <value name="rec_ref">wm.ach.tn.sample.rec:Payments</value>
      </record>
      <record javaclass="com.wm.util.Values">
        <value name="node_type">record</value>
        <value name="field_name">error</value>
        <value name="field_type">recref</value>
        <value name="field_dim">0</value>
        <value name="field_opt">true</value>
        <value name="nillable">true</value>
        <value name="rec_ref">wm.tn.rec:TpaError</value>
      </record>
      <record javaclass="com.wm.util.Values">
        <value name="node_type">record</value>
        <value name="field_name">ccdEntry</value>
        <value name="field_type">recref</value>
        <value name="field_dim">0</value>
        <value name="nillable">true</value>
        <value name="rec_ref">wm.ach.record:CCD_ENTRY_DETAIL</value>
      </record>
      <record javaclass="com.wm.util.Values">
        <value name="node_type">unknown</value>
        <value name="field_name">batchObject</value>
        <value name="field_type">object</value>
        <value name="field_dim">0</value>
        <value name="nillable">true</value>
      </record>
      <record javaclass="com.wm.util.Values">
        <value name="node_type">unknown</value>
        <value name="field_name">success</value>
        <value name="field_type">string</value>
        <value name="field_dim">0</value>
        <value name="nillable">true</value>
      </record>
      <record javaclass="com.wm.util.Values">
        <value name="node_type">unknown</value>
        <value name="field_name">errorMessage</value>
        <value name="field_type">string</value>
        <value name="field_dim">0</value>
        <value name="nillable">true</value>
      </record>
    </array>
  </record>
</Values>
</MAPTARGET>
  <MAPSOURCE>

<Values version="2.0">
  <record name="xml" javaclass="com.wm.util.Values">
    <value name="node_type">record</value>
    <value name="field_name">appendEntryOutput</value>
    <value name="field_type">record</value>
    <value name="field_dim">0</value>
    <value name="nillable">true</value>
    <array name="rec_fields" type="record" depth="1">
    </array>
  </record>
</Values>
</MAPSOURCE>

  <!-- nodes -->

<MAPDELETE NAME="Dropper" FIELD="/ccdEntry;4;0;wm.ach.record:CCD_ENTRY_DETAIL">
</MAPDELETE>
</MAP>
</INVOKE>
</LOOP>

<INVOKE TIMEOUT="" SERVICE="wm.ach.queue:queueBatch" VALIDATE-IN="$none" VALIDATE-OUT="$none">
  <COMMENT>Puts new ACH batch into queue</COMMENT>

  <!-- nodes -->

<MAP MODE="INPUT">
  <MAPTARGET>

<Values version="2.0">
  <record name="xml" javaclass="com.wm.util.Values">
    <value name="node_type">record</value>
    <value name="field_name">queueBatchInput</value>
    <value name="field_type">record</value>
    <value name="field_dim">0</value>
    <value name="nillable">true</value>
    <array name="rec_fields" type="record" depth="1">
      <record javaclass="com.wm.util.Values">
        <value name="node_type">unknown</value>
        <value name="field_name">batchObject</value>
        <value name="field_type">object</value>
        <value name="field_dim">0</value>
        <value name="nillable">true</value>
      </record>
      <record javaclass="com.wm.util.Values">
        <value name="node_type">unknown</value>
        <value name="field_name">originId</value>
        <value name="field_type">string</value>
        <value name="field_dim">0</value>
        <value name="field_opt">true</value>
        <value name="nillable">true</value>
      </record>
      <record javaclass="com.wm.util.Values">
        <value name="node_type">unknown</value>
        <value name="field_name">originName</value>
        <value name="field_type">string</value>
        <value name="field_dim">0</value>
        <value name="field_opt">true</value>
        <value name="nillable">true</value>
      </record>
      <record javaclass="com.wm.util.Values">
        <value name="node_type">unknown</value>
        <value name="field_name">destinationId</value>
        <value name="field_type">string</value>
        <value name="field_dim">0</value>
        <value name="field_opt">true</value>
        <value name="nillable">true</value>
      </record>
      <record javaclass="com.wm.util.Values">
        <value name="node_type">unknown</value>
        <value name="field_name">destinationName</value>
        <value name="field_type">string</value>
        <value name="field_dim">0</value>
        <value name="field_opt">true</value>
        <value name="nillable">true</value>
      </record>
    </array>
  </record>
</Values>
</MAPTARGET>
  <MAPSOURCE>

<Values version="2.0">
  <record name="xml" javaclass="com.wm.util.Values">
    <value name="node_type">record</value>
    <value name="field_type">record</value>
    <value name="field_dim">0</value>
    <value name="nillable">true</value>
    <array name="rec_fields" type="record" depth="1">
      <record javaclass="com.wm.util.Values">
        <value name="node_type">record</value>
        <value name="field_name">entry</value>
        <value name="field_type">record</value>
        <value name="field_dim">0</value>
        <value name="nillable">true</value>
        <array name="rec_fields" type="record" depth="1">
        </array>
      </record>
      <record javaclass="com.wm.util.Values">
        <value name="node_type">record</value>
        <value name="field_name">tpaData</value>
        <value name="field_type">recref</value>
        <value name="field_dim">0</value>
        <value name="nillable">true</value>
        <value name="rec_ref">wm.ach.tn.rec:TPA</value>
      </record>
      <record javaclass="com.wm.util.Values">
        <value name="node_type">record</value>
        <value name="node_comment"></value>
        <record name="node_hints" javaclass="com.wm.util.Values">
          <value name="field_largerEditor">false</value>
          <value name="field_password">false</value>
        </record>
        <value name="field_name">bizdoc</value>
        <value name="field_type">recref</value>
        <value name="field_dim">0</value>
        <value name="nillable">true</value>
        <value name="rec_closed">true</value>
        <value name="rec_ref">wm.tn.rec:BizDocType</value>
      </record>
      <record javaclass="com.wm.util.Values">
        <value name="node_type">record</value>
        <value name="field_name">batchHeader</value>
        <value name="field_type">record</value>
        <value name="field_dim">0</value>
        <value name="nillable">true</value>
        <array name="rec_fields" type="record" depth="1">
          <record javaclass="com.wm.util.Values">
            <value name="node_type">unknown</value>
            <value name="field_name">EFFECTIVE_ENTRY_DATE</value>
            <value name="field_type">string</value>
            <value name="field_dim">0</value>
            <value name="nillable">true</value>
          </record>
        </array>
      </record>
      <record javaclass="com.wm.util.Values">
        <value name="node_type">record</value>
        <value name="field_name">paymentFile</value>
        <value name="field_type">recref</value>
        <value name="field_dim">0</value>
        <value name="nillable">true</value>
        <value name="rec_ref">wm.ach.tn.sample.rec:Payments</value>
      </record>
      <record javaclass="com.wm.util.Values">
        <value name="node_type">record</value>
        <value name="field_name">error</value>
        <value name="field_type">recref</value>
        <value name="field_dim">0</value>
        <value name="field_opt">true</value>
        <value name="nillable">true</value>
        <value name="rec_ref">wm.tn.rec:TpaError</value>
      </record>
      <record javaclass="com.wm.util.Values">
        <value name="node_type">unknown</value>
        <value name="field_name">batchObject</value>
        <value name="field_type">object</value>
        <value name="field_dim">0</value>
        <value name="nillable">true</value>
      </record>
      <record javaclass="com.wm.util.Values">
        <value name="node_type">unknown</value>
        <value name="field_name">success</value>
        <value name="field_type">string</value>
        <value name="field_dim">0</value>
        <value name="nillable">true</value>
      </record>
      <record javaclass="com.wm.util.Values">
        <value name="node_type">unknown</value>
        <value name="field_name">errorMessage</value>
        <value name="field_type">string</value>
        <value name="field_dim">0</value>
        <value name="nillable">true</value>
      </record>
    </array>
  </record>
</Values>
</MAPSOURCE>

  <!-- nodes -->

<MAPCOPY NAME="Link" FROM="/tpaData;4;0;wm.ach.tn.rec:TPA/originId;1;0" TO="/originId;1;0">
</MAPCOPY>

<MAPCOPY NAME="Link" FROM="/tpaData;4;0;wm.ach.tn.rec:TPA/originName;1;0" TO="/originName;1;0">
</MAPCOPY>

<MAPCOPY NAME="Link" FROM="/tpaData;4;0;wm.ach.tn.rec:TPA/destinationId;1;0" TO="/destinationId;1;0">
</MAPCOPY>

<MAPCOPY NAME="Link" FROM="/tpaData;4;0;wm.ach.tn.rec:TPA/destinationName;1;0" TO="/destinationName;1;0">
</MAPCOPY>

<MAPDELETE NAME="Dropper" FIELD="/entry;2;0">
</MAPDELETE>

<MAPDELETE NAME="Dropper" FIELD="/batchHeader;2;0">
</MAPDELETE>
</MAP>

<MAP MODE="OUTPUT">
  <MAPTARGET>

<Values version="2.0">
  <record name="xml" javaclass="com.wm.util.Values">
    <value name="node_type">record</value>
    <value name="field_type">record</value>
    <value name="field_dim">0</value>
    <value name="nillable">true</value>
    <array name="rec_fields" type="record" depth="1">
      <record javaclass="com.wm.util.Values">
        <value name="node_type">record</value>
        <value name="field_name">tpaData</value>
        <value name="field_type">recref</value>
        <value name="field_dim">0</value>
        <value name="nillable">true</value>
        <value name="rec_ref">wm.ach.tn.rec:TPA</value>
      </record>
      <record javaclass="com.wm.util.Values">
        <value name="node_type">unknown</value>
        <value name="field_name">originId</value>
        <value name="field_type">string</value>
        <value name="field_dim">0</value>
        <value name="nillable">true</value>
      </record>
      <record javaclass="com.wm.util.Values">
        <value name="node_type">unknown</value>
        <value name="field_name">originName</value>
        <value name="field_type">string</value>
        <value name="field_dim">0</value>
        <value name="nillable">true</value>
      </record>
      <record javaclass="com.wm.util.Values">
        <value name="node_type">unknown</value>
        <value name="field_name">destinationId</value>
        <value name="field_type">string</value>
        <value name="field_dim">0</value>
        <value name="nillable">true</value>
      </record>
      <record javaclass="com.wm.util.Values">
        <value name="node_type">unknown</value>
        <value name="field_name">destinationName</value>
        <value name="field_type">string</value>
        <value name="field_dim">0</value>
        <value name="nillable">true</value>
      </record>
      <record javaclass="com.wm.util.Values">
        <value name="node_type">record</value>
        <value name="node_comment"></value>
        <record name="node_hints" javaclass="com.wm.util.Values">
          <value name="field_largerEditor">false</value>
          <value name="field_password">false</value>
        </record>
        <value name="field_name">bizdoc</value>
        <value name="field_type">recref</value>
        <value name="field_dim">0</value>
        <value name="nillable">true</value>
        <value name="rec_closed">true</value>
        <value name="rec_ref">wm.tn.rec:BizDocType</value>
      </record>
      <record javaclass="com.wm.util.Values">
        <value name="node_type">record</value>
        <value name="field_name">paymentFile</value>
        <value name="field_type">recref</value>
        <value name="field_dim">0</value>
        <value name="nillable">true</value>
        <value name="rec_ref">wm.ach.tn.sample.rec:Payments</value>
      </record>
      <record javaclass="com.wm.util.Values">
        <value name="node_type">record</value>
        <value name="field_name">error</value>
        <value name="field_type">recref</value>
        <value name="field_dim">0</value>
        <value name="field_opt">true</value>
        <value name="nillable">true</value>
        <value name="rec_ref">wm.tn.rec:TpaError</value>
      </record>
      <record javaclass="com.wm.util.Values">
        <value name="node_type">unknown</value>
        <value name="field_name">batchObject</value>
        <value name="field_type">object</value>
        <value name="field_dim">0</value>
        <value name="nillable">true</value>
      </record>
      <record javaclass="com.wm.util.Values">
        <value name="node_type">unknown</value>
        <value name="field_name">success</value>
        <value name="field_type">string</value>
        <value name="field_dim">0</value>
        <value name="nillable">true</value>
      </record>
      <record javaclass="com.wm.util.Values">
        <value name="node_type">unknown</value>
        <value name="field_name">errorMessage</value>
        <value name="field_type">string</value>
        <value name="field_dim">0</value>
        <value name="nillable">true</value>
      </record>
      <record javaclass="com.wm.util.Values">
        <value name="node_type">unknown</value>
        <value name="field_name">errors</value>
        <value name="field_type">string</value>
        <value name="field_dim">0</value>
        <value name="nillable">true</value>
      </record>
    </array>
  </record>
</Values>
</MAPTARGET>
  <MAPSOURCE>

<Values version="2.0">
  <record name="xml" javaclass="com.wm.util.Values">
    <value name="node_type">record</value>
    <value name="field_name">queueBatchOutput</value>
    <value name="field_type">record</value>
    <value name="field_dim">0</value>
    <value name="nillable">true</value>
    <array name="rec_fields" type="record" depth="1">
    </array>
  </record>
</Values>
</MAPSOURCE>

  <!-- nodes -->

<MAPDELETE NAME="Dropper" FIELD="/destinationName;1;0">
</MAPDELETE>

<MAPDELETE NAME="Dropper" FIELD="/destinationId;1;0">
</MAPDELETE>

<MAPDELETE NAME="Dropper" FIELD="/originName;1;0">
</MAPDELETE>

<MAPDELETE NAME="Dropper" FIELD="/originId;1;0">
</MAPDELETE>
</MAP>
</INVOKE>

<INVOKE TIMEOUT="" SERVICE="wm.ach.tn.trp:send" VALIDATE-IN="$none" VALIDATE-OUT="$none">
  <COMMENT>disable me and invoke from scheduler</COMMENT>

  <!-- nodes -->

<MAP MODE="INPUT">
  <MAPTARGET>

<Values version="2.0">
  <record name="xml" javaclass="com.wm.util.Values">
    <value name="node_type">record</value>
    <value name="field_type">record</value>
    <value name="field_dim">0</value>
    <value name="nillable">true</value>
    <array name="rec_fields" type="record" depth="1">
      <record javaclass="com.wm.util.Values">
        <value name="node_type">unknown</value>
        <value name="node_comment"></value>
        <record name="node_hints" javaclass="com.wm.util.Values">
          <null name="field_usereditable"/>
          <value name="field_largerEditor">false</value>
          <value name="field_password">false</value>
        </record>
        <value name="field_name">fromDate</value>
        <value name="field_type">string</value>
        <value name="field_dim">0</value>
        <value name="field_opt">true</value>
        <value name="nillable">true</value>
      </record>
      <record javaclass="com.wm.util.Values">
        <value name="node_type">unknown</value>
        <value name="field_name">toDate</value>
        <value name="field_type">string</value>
        <value name="field_dim">0</value>
        <value name="field_opt">true</value>
        <value name="nillable">true</value>
      </record>
      <record javaclass="com.wm.util.Values">
        <value name="node_type">unknown</value>
        <value name="field_name">msgType</value>
        <value name="field_type">string</value>
        <value name="field_dim">0</value>
        <value name="field_opt">true</value>
        <value name="nillable">true</value>
      </record>
      <record javaclass="com.wm.util.Values">
        <value name="node_type">unknown</value>
        <value name="field_name">senderId</value>
        <value name="field_type">string</value>
        <value name="field_dim">0</value>
        <value name="field_opt">true</value>
        <value name="nillable">true</value>
      </record>
      <record javaclass="com.wm.util.Values">
        <value name="node_type">unknown</value>
        <value name="node_comment"></value>
        <record name="node_hints" javaclass="com.wm.util.Values">
          <null name="field_usereditable"/>
          <value name="field_largerEditor">false</value>
          <value name="field_password">false</value>
        </record>
        <value name="field_name">receiverId</value>
        <value name="field_type">string</value>
        <value name="field_dim">0</value>
        <value name="field_opt">true</value>
        <value name="nillable">true</value>
      </record>
      <record javaclass="com.wm.util.Values">
        <value name="node_type">record</value>
        <value name="node_comment"></value>
        <record name="node_hints" javaclass="com.wm.util.Values">
          <null name="field_usereditable"/>
          <value name="field_largerEditor">false</value>
          <value name="field_password">false</value>
        </record>
        <value name="field_name">sendSvc</value>
        <value name="field_type">string</value>
        <value name="field_dim">0</value>
        <value name="nillable">true</value>
      </record>
    </array>
  </record>
</Values>
</MAPTARGET>
  <MAPSOURCE>

<Values version="2.0">
  <record name="xml" javaclass="com.wm.util.Values">
    <value name="node_type">record</value>
    <value name="field_type">record</value>
    <value name="field_dim">0</value>
    <value name="nillable">true</value>
    <array name="rec_fields" type="record" depth="1">
      <record javaclass="com.wm.util.Values">
        <value name="node_type">record</value>
        <value name="field_name">tpaData</value>
        <value name="field_type">recref</value>
        <value name="field_dim">0</value>
        <value name="nillable">true</value>
        <value name="rec_ref">wm.ach.tn.rec:TPA</value>
      </record>
      <record javaclass="com.wm.util.Values">
        <value name="node_type">record</value>
        <value name="node_comment"></value>
        <record name="node_hints" javaclass="com.wm.util.Values">
          <value name="field_largerEditor">false</value>
          <value name="field_password">false</value>
        </record>
        <value name="field_name">bizdoc</value>
        <value name="field_type">recref</value>
        <value name="field_dim">0</value>
        <value name="nillable">true</value>
        <value name="rec_closed">true</value>
        <value name="rec_ref">wm.tn.rec:BizDocType</value>
      </record>
      <record javaclass="com.wm.util.Values">
        <value name="node_type">record</value>
        <value name="field_name">paymentFile</value>
        <value name="field_type">recref</value>
        <value name="field_dim">0</value>
        <value name="nillable">true</value>
        <value name="rec_ref">wm.ach.tn.sample.rec:Payments</value>
      </record>
      <record javaclass="com.wm.util.Values">
        <value name="node_type">record</value>
        <value name="field_name">error</value>
        <value name="field_type">recref</value>
        <value name="field_dim">0</value>
        <value name="field_opt">true</value>
        <value name="nillable">true</value>
        <value name="rec_ref">wm.tn.rec:TpaError</value>
      </record>
      <record javaclass="com.wm.util.Values">
        <value name="node_type">unknown</value>
        <value name="field_name">batchObject</value>
        <value name="field_type">object</value>
        <value name="field_dim">0</value>
        <value name="nillable">true</value>
      </record>
      <record javaclass="com.wm.util.Values">
        <value name="node_type">unknown</value>
        <value name="field_name">success</value>
        <value name="field_type">string</value>
        <value name="field_dim">0</value>
        <value name="nillable">true</value>
      </record>
      <record javaclass="com.wm.util.Values">
        <value name="node_type">unknown</value>
        <value name="field_name">errorMessage</value>
        <value name="field_type">string</value>
        <value name="field_dim">0</value>
        <value name="nillable">true</value>
      </record>
      <record javaclass="com.wm.util.Values">
        <value name="node_type">unknown</value>
        <value name="field_name">errors</value>
        <value name="field_type">string</value>
        <value name="field_dim">0</value>
        <value name="nillable">true</value>
      </record>
    </array>
  </record>
</Values>
</MAPSOURCE>

  <!-- nodes -->

<MAPCOPY NAME="Link" FROM="/tpaData;4;0;wm.ach.tn.rec:TPA/Send ISService;1;0" TO="/sendSvc;1;0">
</MAPCOPY>
</MAP>

<MAP MODE="OUTPUT">
  <MAPTARGET>

<Values version="2.0">
  <record name="xml" javaclass="com.wm.util.Values">
    <value name="node_type">record</value>
    <value name="field_type">record</value>
    <value name="field_dim">0</value>
    <value name="nillable">true</value>
    <array name="rec_fields" type="record" depth="1">
      <record javaclass="com.wm.util.Values">
        <value name="node_type">record</value>
        <value name="field_name">tpaData</value>
        <value name="field_type">recref</value>
        <value name="field_dim">0</value>
        <value name="nillable">true</value>
        <value name="rec_ref">wm.ach.tn.rec:TPA</value>
      </record>
      <record javaclass="com.wm.util.Values">
        <value name="node_type">record</value>
        <value name="node_comment"></value>
        <record name="node_hints" javaclass="com.wm.util.Values">
          <value name="field_largerEditor">false</value>
          <value name="field_password">false</value>
        </record>
        <value name="field_name">bizdoc</value>
        <value name="field_type">recref</value>
        <value name="field_dim">0</value>
        <value name="nillable">true</value>
        <value name="rec_closed">true</value>
        <value name="rec_ref">wm.tn.rec:BizDocType</value>
      </record>
      <record javaclass="com.wm.util.Values">
        <value name="node_type">record</value>
        <value name="field_name">paymentFile</value>
        <value name="field_type">recref</value>
        <value name="field_dim">0</value>
        <value name="nillable">true</value>
        <value name="rec_ref">wm.ach.tn.sample.rec:Payments</value>
      </record>
      <record javaclass="com.wm.util.Values">
        <value name="node_type">record</value>
        <value name="field_name">error</value>
        <value name="field_type">recref</value>
        <value name="field_dim">0</value>
        <value name="field_opt">true</value>
        <value name="nillable">true</value>
        <value name="rec_ref">wm.tn.rec:TpaError</value>
      </record>
      <record javaclass="com.wm.util.Values">
        <value name="node_type">unknown</value>
        <value name="field_name">batchObject</value>
        <value name="field_type">object</value>
        <value name="field_dim">0</value>
        <value name="nillable">true</value>
      </record>
      <record javaclass="com.wm.util.Values">
        <value name="node_type">unknown</value>
        <value name="field_name">sendSvc</value>
        <value name="field_type">string</value>
        <value name="field_dim">0</value>
        <value name="nillable">true</value>
      </record>
      <record javaclass="com.wm.util.Values">
        <value name="node_type">unknown</value>
        <value name="field_name">success</value>
        <value name="field_type">string</value>
        <value name="field_dim">0</value>
        <value name="nillable">true</value>
      </record>
      <record javaclass="com.wm.util.Values">
        <value name="node_type">unknown</value>
        <value name="field_name">errorMessage</value>
        <value name="field_type">string</value>
        <value name="field_dim">0</value>
        <value name="nillable">true</value>
      </record>
      <record javaclass="com.wm.util.Values">
        <value name="node_type">unknown</value>
        <value name="field_name">errors</value>
        <value name="field_type">string</value>
        <value name="field_dim">0</value>
        <value name="nillable">true</value>
      </record>
    </array>
  </record>
</Values>
</MAPTARGET>
  <MAPSOURCE>

<Values version="2.0">
  <record name="xml" javaclass="com.wm.util.Values">
    <value name="node_type">record</value>
    <value name="field_type">record</value>
    <value name="field_dim">0</value>
    <value name="nillable">true</value>
    <array name="rec_fields" type="record" depth="1">
    </array>
  </record>
</Values>
</MAPSOURCE>

  <!-- nodes -->

<MAPDELETE NAME="Dropper" FIELD="/sendSvc;1;0">
</MAPDELETE>
</MAP>
</INVOKE>
</FLOW>
